[
  {
    "index": "232",
    "rarity": 960.3333333333334
  },
  {
    "index": "90",
    "rarity": 801.2083333333333
  },
  {
    "index": "123",
    "rarity": 801.2083333333333
  },
  {
    "index": "217",
    "rarity": 801.2083333333333
  },
  {
    "index": "109",
    "rarity": 796.9866666666667
  },
  {
    "index": "204",
    "rarity": 796.9866666666667
  },
  {
    "index": "210",
    "rarity": 796.9866666666667
  },
  {
    "index": "68",
    "rarity": 630.6369047619047
  },
  {
    "index": "185",
    "rarity": 630.6369047619047
  },
  {
    "index": "199",
    "rarity": 630.6369047619047
  },
  {
    "index": "100",
    "rarity": 624.3194444444443
  },
  {
    "index": "126",
    "rarity": 624.3194444444443
  },
  {
    "index": "173",
    "rarity": 624.3194444444443
  },
  {
    "index": "203",
    "rarity": 624.3194444444443
  },
  {
    "index": "277",
    "rarity": 624.3194444444443
  },
  {
    "index": "67",
    "rarity": 616.0775757575758
  },
  {
    "index": "124",
    "rarity": 613.2943589743589
  },
  {
    "index": "19",
    "rarity": 610.4241666666667
  },
  {
    "index": "77",
    "rarity": 610.4241666666667
  },
  {
    "index": "117",
    "rarity": 609.0422222222222
  },
  {
    "index": "175",
    "rarity": 599.0101010101009
  },
  {
    "index": "163",
    "rarity": 577.7083333333333
  },
  {
    "index": "151",
    "rarity": 540.4583333333333
  },
  {
    "index": "26",
    "rarity": 526.0775757575757
  },
  {
    "index": "38",
    "rarity": 526.0775757575757
  },
  {
    "index": "181",
    "rarity": 526.0775757575757
  },
  {
    "index": "188",
    "rarity": 526.0775757575757
  },
  {
    "index": "216",
    "rarity": 526.0775757575757
  },
  {
    "index": "8",
    "rarity": 517.6116666666667
  },
  {
    "index": "49",
    "rarity": 515.32
  },
  {
    "index": "116",
    "rarity": 515.32
  },
  {
    "index": "206",
    "rarity": 508.59956989247314
  },
  {
    "index": "239",
    "rarity": 482.15333333333336
  },
  {
    "index": "111",
    "rarity": 481.63690476190476
  },
  {
    "index": "146",
    "rarity": 473.10833333333335
  },
  {
    "index": "40",
    "rarity": 467.07757575757574
  },
  {
    "index": "255",
    "rarity": 461.4241666666667
  },
  {
    "index": "261",
    "rarity": 461.4241666666667
  },
  {
    "index": "160",
    "rarity": 450.01010101010104
  },
  {
    "index": "168",
    "rarity": 431.97023809523813
  },
  {
    "index": "256",
    "rarity": 431.97023809523813
  },
  {
    "index": "184",
    "rarity": 424.2366666666667
  },
  {
    "index": "250",
    "rarity": 424.2366666666667
  },
  {
    "index": "272",
    "rarity": 424.2366666666667
  },
  {
    "index": "279",
    "rarity": 424.2366666666667
  },
  {
    "index": "281",
    "rarity": 407.65333333333336
  },
  {
    "index": "30",
    "rarity": 403.70833333333337
  },
  {
    "index": "222",
    "rarity": 403.70833333333337
  },
  {
    "index": "6",
    "rarity": 400.34343434343435
  },
  {
    "index": "101",
    "rarity": 400.3434343434343
  },
  {
    "index": "218",
    "rarity": 399.4866666666667
  },
  {
    "index": "87",
    "rarity": 399.43111111111114
  },
  {
    "index": "251",
    "rarity": 392.57757575757574
  },
  {
    "index": "227",
    "rarity": 386.9241666666667
  },
  {
    "index": "237",
    "rarity": 375.9329032258065
  },
  {
    "index": "57",
    "rarity": 375.510101010101
  },
  {
    "index": "293",
    "rarity": 367.7442424242424
  },
  {
    "index": "228",
    "rarity": 362.0908333333333
  },
  {
    "index": "95",
    "rarity": 361.3583333333333
  },
  {
    "index": "155",
    "rarity": 361.3583333333333
  },
  {
    "index": "219",
    "rarity": 361.3583333333333
  },
  {
    "index": "226",
    "rarity": 361.3583333333333
  },
  {
    "index": "258",
    "rarity": 361.3583333333333
  },
  {
    "index": "286",
    "rarity": 361.3583333333333
  },
  {
    "index": "296",
    "rarity": 361.3583333333333
  },
  {
    "index": "3",
    "rarity": 360.6490043290043
  },
  {
    "index": "62",
    "rarity": 360.6490043290043
  },
  {
    "index": "143",
    "rarity": 360.610101010101
  },
  {
    "index": "55",
    "rarity": 350.67676767676767
  },
  {
    "index": "141",
    "rarity": 350.67676767676767
  },
  {
    "index": "214",
    "rarity": 350.67676767676767
  },
  {
    "index": "282",
    "rarity": 349.9866666666667
  },
  {
    "index": "133",
    "rarity": 349.82
  },
  {
    "index": "61",
    "rarity": 349.68666666666667
  },
  {
    "index": "170",
    "rarity": 349.68666666666667
  },
  {
    "index": "262",
    "rarity": 349.6811111111111
  },
  {
    "index": "125",
    "rarity": 349.39015151515144
  },
  {
    "index": "136",
    "rarity": 349.39015151515144
  },
  {
    "index": "189",
    "rarity": 349.39015151515144
  },
  {
    "index": "196",
    "rarity": 349.39015151515144
  },
  {
    "index": "245",
    "rarity": 349.39015151515144
  },
  {
    "index": "260",
    "rarity": 349.39015151515144
  },
  {
    "index": "65",
    "rarity": 345.53527777777776
  },
  {
    "index": "74",
    "rarity": 335.4866666666667
  },
  {
    "index": "75",
    "rarity": 335.4866666666667
  },
  {
    "index": "266",
    "rarity": 335.4866666666667
  },
  {
    "index": "254",
    "rarity": 333.12
  },
  {
    "index": "63",
    "rarity": 331.0491666666667
  },
  {
    "index": "97",
    "rarity": 326.18290322580646
  },
  {
    "index": "284",
    "rarity": 326.18290322580646
  },
  {
    "index": "287",
    "rarity": 326.18290322580646
  },
  {
    "index": "27",
    "rarity": 322.8662365591398
  },
  {
    "index": "295",
    "rarity": 322.03706989247314
  },
  {
    "index": "60",
    "rarity": 321.1888725490196
  },
  {
    "index": "224",
    "rarity": 321.1888725490196
  },
  {
    "index": "2",
    "rarity": 320.87676767676766
  },
  {
    "index": "80",
    "rarity": 320.87676767676766
  },
  {
    "index": "147",
    "rarity": 320.87676767676766
  },
  {
    "index": "288",
    "rarity": 320.87676767676766
  },
  {
    "index": "236",
    "rarity": 319.635101010101
  },
  {
    "index": "11",
    "rarity": 311.0422222222222
  },
  {
    "index": "29",
    "rarity": 311.0422222222222
  },
  {
    "index": "91",
    "rarity": 311.0422222222222
  },
  {
    "index": "119",
    "rarity": 311.0422222222222
  },
  {
    "index": "130",
    "rarity": 311.0422222222222
  },
  {
    "index": "270",
    "rarity": 311.0422222222222
  },
  {
    "index": "106",
    "rarity": 310.62300423590744
  },
  {
    "index": "191",
    "rarity": 310.62300423590744
  },
  {
    "index": "211",
    "rarity": 310.62300423590744
  },
  {
    "index": "271",
    "rarity": 310.62300423590744
  },
  {
    "index": "45",
    "rarity": 309.7748068924539
  },
  {
    "index": "48",
    "rarity": 309.7748068924539
  },
  {
    "index": "265",
    "rarity": 282.97023809523813
  },
  {
    "index": "70",
    "rarity": 279.4583333333333
  },
  {
    "index": "135",
    "rarity": 279.4583333333333
  },
  {
    "index": "152",
    "rarity": 279.4583333333333
  },
  {
    "index": "174",
    "rarity": 279.4583333333333
  },
  {
    "index": "223",
    "rarity": 268.4109090909091
  },
  {
    "index": "243",
    "rarity": 268.4109090909091
  },
  {
    "index": "35",
    "rarity": 251.34343434343435
  },
  {
    "index": "176",
    "rarity": 251.34343434343435
  },
  {
    "index": "110",
    "rarity": 247.94424242424242
  },
  {
    "index": "280",
    "rarity": 247.94424242424242
  },
  {
    "index": "285",
    "rarity": 237.6904789833822
  },
  {
    "index": "190",
    "rarity": 236.8422816399287
  },
  {
    "index": "268",
    "rarity": 228.67757575757577
  },
  {
    "index": "76",
    "rarity": 226.510101010101
  },
  {
    "index": "81",
    "rarity": 226.510101010101
  },
  {
    "index": "105",
    "rarity": 226.510101010101
  },
  {
    "index": "298",
    "rarity": 226.510101010101
  },
  {
    "index": "79",
    "rarity": 211.7088888888889
  },
  {
    "index": "83",
    "rarity": 211.7088888888889
  },
  {
    "index": "138",
    "rarity": 211.7088888888889
  },
  {
    "index": "180",
    "rarity": 211.7088888888889
  },
  {
    "index": "241",
    "rarity": 211.7088888888889
  },
  {
    "index": "257",
    "rarity": 211.7088888888889
  },
  {
    "index": "28",
    "rarity": 211.610101010101
  },
  {
    "index": "200",
    "rarity": 208.98666666666668
  },
  {
    "index": "89",
    "rarity": 204.02000000000004
  },
  {
    "index": "244",
    "rarity": 202.1527777777778
  },
  {
    "index": "158",
    "rarity": 200.68666666666667
  },
  {
    "index": "161",
    "rarity": 197.36444444444447
  },
  {
    "index": "13",
    "rarity": 192.9180392156863
  },
  {
    "index": "115",
    "rarity": 186.48666666666668
  },
  {
    "index": "156",
    "rarity": 186.48666666666668
  },
  {
    "index": "220",
    "rarity": 186.48666666666668
  },
  {
    "index": "18",
    "rarity": 185.12121212121212
  },
  {
    "index": "31",
    "rarity": 185.12121212121212
  },
  {
    "index": "71",
    "rarity": 185.12121212121212
  },
  {
    "index": "144",
    "rarity": 185.12121212121212
  },
  {
    "index": "150",
    "rarity": 185.12121212121212
  },
  {
    "index": "164",
    "rarity": 185.12121212121212
  },
  {
    "index": "242",
    "rarity": 184.7212365591398
  },
  {
    "index": "17",
    "rarity": 177.31944444444443
  },
  {
    "index": "114",
    "rarity": 177.31944444444443
  },
  {
    "index": "179",
    "rarity": 177.31944444444443
  },
  {
    "index": "294",
    "rarity": 173.86623655913982
  },
  {
    "index": "47",
    "rarity": 173.03706989247314
  },
  {
    "index": "43",
    "rarity": 171.87676767676768
  },
  {
    "index": "88",
    "rarity": 171.87676767676768
  },
  {
    "index": "253",
    "rarity": 171.87676767676768
  },
  {
    "index": "16",
    "rarity": 170.635101010101
  },
  {
    "index": "113",
    "rarity": 170.635101010101
  },
  {
    "index": "240",
    "rarity": 170.635101010101
  },
  {
    "index": "51",
    "rarity": 167.59777777777776
  },
  {
    "index": "195",
    "rarity": 162.6916666666667
  },
  {
    "index": "229",
    "rarity": 161.94343434343435
  },
  {
    "index": "41",
    "rarity": 161.62300423590747
  },
  {
    "index": "46",
    "rarity": 161.62300423590747
  },
  {
    "index": "167",
    "rarity": 161.62300423590747
  },
  {
    "index": "221",
    "rarity": 161.62300423590747
  },
  {
    "index": "297",
    "rarity": 160.77480689245394
  },
  {
    "index": "50",
    "rarity": 152.43290322580646
  },
  {
    "index": "1",
    "rarity": 152.01010101010104
  },
  {
    "index": "274",
    "rarity": 152.01010101010104
  },
  {
    "index": "145",
    "rarity": 151.58470588235295
  },
  {
    "index": "259",
    "rarity": 151.02
  },
  {
    "index": "85",
    "rarity": 144.09956989247314
  },
  {
    "index": "247",
    "rarity": 144.09956989247314
  },
  {
    "index": "234",
    "rarity": 144.0025396825397
  },
  {
    "index": "5",
    "rarity": 142.76444444444445
  },
  {
    "index": "264",
    "rarity": 139.59343434343435
  },
  {
    "index": "246",
    "rarity": 139.42000000000002
  },
  {
    "index": "23",
    "rarity": 137.14900432900433
  },
  {
    "index": "56",
    "rarity": 136.82000000000002
  },
  {
    "index": "104",
    "rarity": 136.82000000000002
  },
  {
    "index": "248",
    "rarity": 136.82000000000002
  },
  {
    "index": "289",
    "rarity": 133.62416666666667
  },
  {
    "index": "4",
    "rarity": 132.2422222222222
  },
  {
    "index": "86",
    "rarity": 132.2422222222222
  },
  {
    "index": "148",
    "rarity": 132.2422222222222
  },
  {
    "index": "171",
    "rarity": 132.2422222222222
  },
  {
    "index": "292",
    "rarity": 132.2422222222222
  },
  {
    "index": "193",
    "rarity": 128.27833333333334
  },
  {
    "index": "84",
    "rarity": 127.5162365591398
  },
  {
    "index": "177",
    "rarity": 127.5162365591398
  },
  {
    "index": "273",
    "rarity": 127.5162365591398
  },
  {
    "index": "37",
    "rarity": 127.17676767676768
  },
  {
    "index": "102",
    "rarity": 126.66803921568629
  },
  {
    "index": "201",
    "rarity": 124.19956989247312
  },
  {
    "index": "32",
    "rarity": 122.21010101010103
  },
  {
    "index": "33",
    "rarity": 111.9563375692408
  },
  {
    "index": "44",
    "rarity": 111.9563375692408
  },
  {
    "index": "59",
    "rarity": 111.9563375692408
  },
  {
    "index": "92",
    "rarity": 111.9563375692408
  },
  {
    "index": "149",
    "rarity": 111.9563375692408
  },
  {
    "index": "202",
    "rarity": 111.9563375692408
  },
  {
    "index": "233",
    "rarity": 111.9563375692408
  },
  {
    "index": "103",
    "rarity": 111.1081402257873
  },
  {
    "index": "197",
    "rarity": 111.1081402257873
  },
  {
    "index": "225",
    "rarity": 111.1081402257873
  },
  {
    "index": "9",
    "rarity": 110.99015151515152
  },
  {
    "index": "96",
    "rarity": 110.99015151515152
  },
  {
    "index": "134",
    "rarity": 110.99015151515152
  },
  {
    "index": "165",
    "rarity": 110.99015151515152
  },
  {
    "index": "205",
    "rarity": 110.99015151515152
  },
  {
    "index": "137",
    "rarity": 110.62121212121212
  },
  {
    "index": "291",
    "rarity": 109.61999999999999
  },
  {
    "index": "10",
    "rarity": 105.18152958152959
  },
  {
    "index": "24",
    "rarity": 105.18152958152959
  },
  {
    "index": "186",
    "rarity": 104.3662365591398
  },
  {
    "index": "69",
    "rarity": 104.17561497326204
  },
  {
    "index": "22",
    "rarity": 102.34343434343435
  },
  {
    "index": "159",
    "rarity": 102.34343434343435
  },
  {
    "index": "207",
    "rarity": 102.34343434343435
  },
  {
    "index": "99",
    "rarity": 101.35333333333335
  },
  {
    "index": "58",
    "rarity": 98.51803921568627
  },
  {
    "index": "278",
    "rarity": 96.79500000000002
  },
  {
    "index": "42",
    "rarity": 96.13510101010101
  },
  {
    "index": "182",
    "rarity": 96.13510101010101
  },
  {
    "index": "252",
    "rarity": 96.13510101010101
  },
  {
    "index": "290",
    "rarity": 95.72121212121212
  },
  {
    "index": "132",
    "rarity": 94.25253968253969
  },
  {
    "index": "187",
    "rarity": 92.27000000000001
  },
  {
    "index": "142",
    "rarity": 91.79435897435899
  },
  {
    "index": "34",
    "rarity": 87.78290322580645
  },
  {
    "index": "213",
    "rarity": 87.78290322580645
  },
  {
    "index": "39",
    "rarity": 87.12300423590746
  },
  {
    "index": "112",
    "rarity": 87.12300423590746
  },
  {
    "index": "139",
    "rarity": 87.12300423590746
  },
  {
    "index": "166",
    "rarity": 87.12300423590746
  },
  {
    "index": "209",
    "rarity": 87.12300423590746
  },
  {
    "index": "238",
    "rarity": 87.12300423590746
  },
  {
    "index": "15",
    "rarity": 86.27480689245395
  },
  {
    "index": "25",
    "rarity": 86.27480689245395
  },
  {
    "index": "153",
    "rarity": 86.27480689245395
  },
  {
    "index": "215",
    "rarity": 86.27480689245395
  },
  {
    "index": "98",
    "rarity": 83.61803921568627
  },
  {
    "index": "162",
    "rarity": 82.515670995671
  },
  {
    "index": "94",
    "rarity": 80.05809523809523
  },
  {
    "index": "194",
    "rarity": 80.05809523809523
  },
  {
    "index": "208",
    "rarity": 80.05809523809523
  },
  {
    "index": "140",
    "rarity": 73.70373655913978
  },
  {
    "index": "107",
    "rarity": 72.85553921568628
  },
  {
    "index": "263",
    "rarity": 72.85553921568628
  },
  {
    "index": "122",
    "rarity": 72.54343434343434
  },
  {
    "index": "20",
    "rarity": 72.22300423590747
  },
  {
    "index": "36",
    "rarity": 72.22300423590747
  },
  {
    "index": "276",
    "rarity": 71.37480689245395
  },
  {
    "index": "249",
    "rarity": 70.31166666666667
  },
  {
    "index": "157",
    "rarity": 68.2311111111111
  },
  {
    "index": "78",
    "rarity": 66.58946778711484
  },
  {
    "index": "93",
    "rarity": 65.44819624819624
  },
  {
    "index": "21",
    "rarity": 62.28967090257413
  },
  {
    "index": "198",
    "rarity": 62.28967090257413
  },
  {
    "index": "7",
    "rarity": 61.994358974358974
  },
  {
    "index": "129",
    "rarity": 61.994358974358974
  },
  {
    "index": "64",
    "rarity": 61.29956989247312
  },
  {
    "index": "172",
    "rarity": 61.29956989247312
  },
  {
    "index": "267",
    "rarity": 60.969242424242424
  },
  {
    "index": "131",
    "rarity": 60.75269230769231
  },
  {
    "index": "178",
    "rarity": 60.75269230769231
  },
  {
    "index": "269",
    "rarity": 60.45137254901961
  },
  {
    "index": "283",
    "rarity": 60.45137254901961
  },
  {
    "index": "169",
    "rarity": 58.88510101010101
  },
  {
    "index": "275",
    "rarity": 55.987878787878785
  },
  {
    "index": "12",
    "rarity": 54.34623546388252
  },
  {
    "index": "108",
    "rarity": 51.74059553349876
  },
  {
    "index": "120",
    "rarity": 51.74059553349876
  },
  {
    "index": "231",
    "rarity": 51.74059553349876
  },
  {
    "index": "72",
    "rarity": 50.89239819004525
  },
  {
    "index": "82",
    "rarity": 50.89239819004525
  },
  {
    "index": "128",
    "rarity": 50.89239819004525
  },
  {
    "index": "154",
    "rarity": 50.89239819004525
  },
  {
    "index": "14",
    "rarity": 49.87300423590746
  },
  {
    "index": "53",
    "rarity": 49.87300423590746
  },
  {
    "index": "235",
    "rarity": 49.87300423590746
  },
  {
    "index": "183",
    "rarity": 49.02480689245395
  },
  {
    "index": "212",
    "rarity": 47.09956989247312
  },
  {
    "index": "52",
    "rarity": 46.25137254901961
  },
  {
    "index": "118",
    "rarity": 44.73290322580645
  },
  {
    "index": "121",
    "rarity": 44.73290322580645
  },
  {
    "index": "192",
    "rarity": 44.73290322580645
  },
  {
    "index": "73",
    "rarity": 32.48967090257413
  },
  {
    "index": "127",
    "rarity": 32.48967090257413
  },
  {
    "index": "230",
    "rarity": 32.48967090257413
  },
  {
    "index": "54",
    "rarity": 31.64147355912062
  },
  {
    "index": "66",
    "rarity": 31.64147355912062
  }
]